Metadata-Version: 1.0
Name: pentas
Version: 0.0.1
Summary: Simple functions for plotting relevant informations
Home-page: https://github.com/caiocarneloz/pentas
Author: Caio Carneloz
Author-email: caiocarneloz@gmail.com
License: MIT License
Keywords: plotting
Platform: UNKNOWN
